colorstreak/__init__.py
colorstreak/logger.py
colorstreak-2.1.3.dist-info/METADATA
colorstreak-2.1.3.dist-info/WHEEL
colorstreak-2.1.3.dist-info/top_level.txt
colorstreak-2.1.3.dist-info/RECORD
