Metadata-Version: 2.4
Name: colorstreak
Version: 2.1.3
Summary: Minimal color logger for Python terminals (print-compatible)
Requires-Python: >=3.10
Requires-Dist: python-dotenv>=1.2.1
Requires-Dist: typer>=0.21.1
